{
  "id": "ocr-ocr-es-es-27",
  "type": "extracted-text",
  "product": "e-orbit",
  "summary": "Es) Es",
  "language": "es-CO",
  "validation_status": "inferred-but-unverified",
  "confidence": "ocr-fallback-low",
  "ocr_dependency": "full",
  "channel_targets": [
    "web",
    "pdf",
    "support",
    "onboarding",
    "chatbot",
    "rag",
    "api"
  ],
  "source_refs": [
    "generated_manuals/e-orbit/manual.json#section-27"
  ],
  "extraction_lineage": [
    "knowledge/extracted-text/ocr-ocr-es-es-27.json"
  ],
  "schema_version": "knowledge-core/1.0",
  "updated_at": "2026-05-13T15:18:31Z",
  "related": {},
  "semantic_category": "General",
  "raw_text": "ings\nNM\n\"Success\"\n(Please refer to the appendix of the manual for detailed operation of networked products).\nNote: The distribution function only supports one mobile phone for distribution. If you enter the networking\nconfiguration again, the last distribution data will be automatically cleared. Users should be cautious when\noperating.\n@Volume\n| 3.System settings |\nsettings",
  "legacy_storage_bucket": "extracted-text"
}